dstack_mgmt/__init__.py
dstack_mgmt/cli.py
dstack_mgmt/config.py
dstack_mgmt/manager.py
dstack_mgmt/templates/fleet.yml
dstack_mgmt/templates/ide.yml
dstack_mgmt/templates/service.yml
dstack_mgmt/templates/task.yml
dstack_yaml_manager-0.1.4.dist-info/licenses/LICENSE
dstack_yaml_manager-0.1.4.dist-info/METADATA
dstack_yaml_manager-0.1.4.dist-info/WHEEL
dstack_yaml_manager-0.1.4.dist-info/entry_points.txt
dstack_yaml_manager-0.1.4.dist-info/top_level.txt
dstack_yaml_manager-0.1.4.dist-info/RECORD
