Metadata-Version: 2.4
Name: dstack-yaml-manager
Version: 0.1.4
Summary: A Terminal User Interface for managing dstack YAML configurations
Home-page: https://github.com/dstack-mgmt/dstack-mgmt-tool
Author: dstack Management Tool Contributors
Author-email: 
Project-URL: Bug Reports, https://github.com/dstack-mgmt/dstack-mgmt-tool/issues
Project-URL: Source, https://github.com/dstack-mgmt/dstack-mgmt-tool
Project-URL: Documentation, https://github.com/dstack-mgmt/dstack-mgmt-tool#readme
Keywords: dstack yaml tui management terminal cli
Classifier: Development Status :: 4 - Beta
Classifier: Intended Audience :: Developers
Classifier: Topic :: Software Development
Classifier: Topic :: System :: Systems Administration
Classifier: Topic :: Utilities
Classifier: License :: OSI Approved :: MIT License
Classifier: Programming Language :: Python :: 3
Classifier: Programming Language :: Python :: 3.8
Classifier: Programming Language :: Python :: 3.9
Classifier: Programming Language :: Python :: 3.10
Classifier: Programming Language :: Python :: 3.11
Classifier: Programming Language :: Python :: 3.12
Classifier: Environment :: Console
Classifier: Operating System :: OS Independent
Requires-Python: >=3.8
License-File: LICENSE
Requires-Dist: textual>=0.38.0
Requires-Dist: rich>=13.0.0
Requires-Dist: PyYAML>=6.0
Provides-Extra: dev
Requires-Dist: pytest>=7.0.0; extra == "dev"
Requires-Dist: black>=23.0.0; extra == "dev"
Requires-Dist: flake8>=6.0.0; extra == "dev"
Requires-Dist: mypy>=1.0.0; extra == "dev"
Dynamic: author
Dynamic: classifier
Dynamic: description
Dynamic: description-content-type
Dynamic: home-page
Dynamic: keywords
Dynamic: license-file
Dynamic: project-url
Dynamic: provides-extra
Dynamic: requires-dist
Dynamic: requires-python
Dynamic: summary
